{
  "audio_file": "C:\\Users\\mark\\CODE\\ironline-podcast\\audio\\the-future-economy\\2026-04-09_ep002.mp3",
  "audio_filename": "2026-04-09_ep002.mp3",
  "generated_at": "2026-04-09T19:57:59Z",
  "voice_id": "ZthjuvLPty3kTMaNKVKb",
  "model_id": "eleven_v3",
  "characters_used": 45797,
  "file_size_bytes": 52927068,
  "series": "the-future-economy",
  "episode": 2,
  "chunks": 11,
  "request_stitching": true,
  "voice_settings": {
    "stability": 0.75,
    "similarity_boost": 0.85,
    "style": 0.15,
    "use_speaker_boost": true,
    "speed": 0.93
  }
}